Metadata-Version: 2.4
Name: grain-nightly
Version: 0.0.16
Summary: Grain: A library for loading and transforming data for ML training.
Author-email: Grain team <grain-dev@google.com>
License:                                  Apache License
Project-URL: homepage, https://github.com/google/grain
Classifier: Programming Language :: Python :: 3
Classifier: License :: OSI Approved :: Apache Software License
Classifier: Operating System :: POSIX :: Linux
Requires-Python: >=3.10
License-File: LICENSE
Requires-Dist: absl-py
Requires-Dist: array-record
Requires-Dist: cloudpickle
Requires-Dist: dm-tree
Requires-Dist: etils[epath,epy]
Requires-Dist: more-itertools>=9.1.0
Requires-Dist: numpy
Requires-Dist: protobuf>=3.20.3
Provides-Extra: testing
Requires-Dist: attrs; extra == "testing"
Requires-Dist: dill; extra == "testing"
Requires-Dist: jax; extra == "testing"
Requires-Dist: jaxlib; extra == "testing"
Requires-Dist: jaxtyping; extra == "testing"
Requires-Dist: pyarrow; extra == "testing"
Requires-Dist: tensorflow-datasets; extra == "testing"
Provides-Extra: parquet
Requires-Dist: pyarrow; extra == "parquet"
Dynamic: license-file
